grai_source_dbt/__init__.py
grai_source_dbt/adapters/__init__.py
grai_source_dbt/adapters/adapters.py
grai_source_dbt/adapters/v5.py
grai_source_dbt/base.py
grai_source_dbt/data/graph.gpickle
grai_source_dbt/data/manifest.json
grai_source_dbt/data_tools.py
grai_source_dbt/loaders/__init__.py
grai_source_dbt/loaders/base.py
grai_source_dbt/loaders/utils.py
grai_source_dbt/loaders/v1.py
grai_source_dbt/loaders/v10.py
grai_source_dbt/loaders/v11.py
grai_source_dbt/loaders/v2.py
grai_source_dbt/loaders/v3.py
grai_source_dbt/loaders/v4.py
grai_source_dbt/loaders/v5.py
grai_source_dbt/loaders/v6.py
grai_source_dbt/loaders/v7.py
grai_source_dbt/loaders/v8.py
grai_source_dbt/loaders/v9.py
grai_source_dbt/models/__init__.py
grai_source_dbt/models/grai.py
grai_source_dbt/models/shared.py
grai_source_dbt/package_definitions.py
grai_source_dbt/processor.py
grai_source_dbt/py.typed
grai_source_dbt/utils.py
grai_source_dbt-0.3.5.dist-info/METADATA
grai_source_dbt-0.3.5.dist-info/WHEEL
grai_source_dbt-0.3.5.dist-info/RECORD
